{
  "communities": {
    "0": [
      "autodirezione",
      "autovalutazione",
      "character_skills",
      "competenze_strategiche",
      "filippo_epifani",
      "piattaforma_comp_strategiche_document",
      "qap",
      "qpcc",
      "qpcs",
      "qsa",
      "qsar",
      "ztpi"
    ],
    "1": [
      "abiti",
      "carattere",
      "cognitive_skills",
      "general_educational_development",
      "heckman_james",
      "imparare_a_dirigere_se_stessi_document",
      "metacognizione",
      "motivazione",
      "non_cognitive_skills",
      "promuovere_la_crescita_nelle_competenze_strategiche_document",
      "vittadini_giorgio"
    ],
    "2": [
      "autodeterminazione",
      "life_design",
      "mark_savickas",
      "michele_pellerey",
      "orientamento_professionale",
      "soft_skill",
      "soft_skill_document",
      "soft_skill_scheda_document"
    ],
    "3": [
      "apprendimento_permanente",
      "autoregolazione",
      "emad_samir_anis_matta",
      "giuseppe_crea",
      "hard_skills",
      "sergio_melogno",
      "strumenti_e_metodologie_document"
    ],
    "4": [
      "ciofs_fp",
      "enrica_ottone",
      "identita_professionale",
      "mahara",
      "massimo_margottini",
      "portfolio_digitale",
      "riflessivita"
    ],
    "5": [
      "cnos_fap",
      "dariusz_grzadziel",
      "dimensioni_morali",
      "dimensioni_spirituali",
      "marco_bay",
      "promuovere_la_crescita_document"
    ],
    "6": [
      "centro_ricerca_formazione_distanza",
      "epifani_filippo",
      "margottini_massimo",
      "piattaforma_comp_strategiche_margottini_epifani_document",
      "universita_roma_tre"
    ]
  },
  "cohesion": {
    "0": 0.30303030303030304,
    "1": 0.23636363636363636,
    "2": 0.39285714285714285,
    "3": 0.2857142857142857,
    "4": 0.2857142857142857,
    "5": 0.3333333333333333,
    "6": 0.4
  },
  "gods": [
    {
      "id": "imparare_a_dirigere_se_stessi_document",
      "label": "Imparare a dirigere se stessi",
      "degree": 24
    },
    {
      "id": "strumenti_e_metodologie_document",
      "label": "Strumenti e metodologie di orientamento formativo e professionale nel quadro dei processi di apprendimento permanente",
      "degree": 24
    },
    {
      "id": "competenze_strategiche",
      "label": "Competenze strategiche",
      "degree": 18
    },
    {
      "id": "portfolio_digitale",
      "label": "Portfolio digitale",
      "degree": 13
    },
    {
      "id": "piattaforma_comp_strategiche_document",
      "label": "Promuovere l'autovalutazione di competenze strategiche. Aggiornamenti e sviluppi della piattaforma competenzestrategiche.it",
      "degree": 13
    },
    {
      "id": "soft_skill_document",
      "label": "Soft skill e orientamento professionale",
      "degree": 10
    },
    {
      "id": "autovalutazione",
      "label": "Autovalutazione",
      "degree": 8
    },
    {
      "id": "promuovere_la_crescita_document",
      "label": "Promuovere la crescita nelle competenze strategiche che hanno le loro radici nelle dimensioni morali e spirituali della persona. Rapporto di ricerca",
      "degree": 8
    },
    {
      "id": "piattaforma_comp_strategiche_margottini_epifani_document",
      "label": "Promuovere l'autovalutazione di competenze strategiche. Aggiornamenti e sviluppi della piattaforma competenzestrategiche.it",
      "degree": 4
    },
    {
      "id": "heckman_james",
      "label": "James Heckman",
      "degree": 4
    }
  ],
  "surprises": [
    {
      "source": "Promuovere la crescita nelle competenze strategiche che hanno le loro radici nelle dimensioni morali e spirituali della persona. Rapporto di ricerca",
      "target": "Competenze strategiche",
      "source_files": [
        "schede-bibliografiche/promuovere_la_crescita_nelle_competenze_strategiche.PDF.md",
        "Imparare_a_dirigere_se_stessi.pdf"
      ],
      "confidence": "EXTRACTED",
      "relation": "conceptually_related_to",
      "why": "crosses file types (paper \u2194 doc); connects across different repos/directories; bridges separate communities"
    },
    {
      "source": "Promuovere la crescita nelle competenze strategiche che hanno le loro radici nelle dimensioni morali e spirituali della persona. Rapporto di ricerca",
      "target": "Autovalutazione",
      "source_files": [
        "schede-bibliografiche/promuovere_la_crescita_nelle_competenze_strategiche.PDF.md",
        "piattaforma_comp._strategiche_-_margottini_epifani.pdf"
      ],
      "confidence": "EXTRACTED",
      "relation": "conceptually_related_to",
      "why": "crosses file types (paper \u2194 doc); connects across different repos/directories; bridges separate communities"
    },
    {
      "source": "Strumenti e metodologie di orientamento formativo e professionale nel quadro dei processi di apprendimento permanente",
      "target": "Imparare a dirigere se stessi",
      "source_files": [
        "strumenti_e_metodologie.pdf",
        "Imparare_a_dirigere_se_stessi.pdf"
      ],
      "confidence": "INFERRED",
      "relation": "cites",
      "why": "inferred connection - not explicitly stated in source; connects across different repos/directories; bridges separate communities"
    },
    {
      "source": "Promuovere la crescita nelle competenze strategiche",
      "target": "Competenze strategiche",
      "source_files": [
        "promuovere_la_crescita_nelle_competenze_strategiche.PDF",
        "Imparare_a_dirigere_se_stessi.pdf"
      ],
      "confidence": "EXTRACTED",
      "relation": "cites",
      "why": "connects across different repos/directories; bridges separate communities; peripheral node `Promuovere la crescita nelle competenze strategiche` unexpectedly reaches hub `Competenze strategiche`"
    },
    {
      "source": "Competenze strategiche",
      "target": "Portfolio digitale",
      "source_files": [
        "Imparare_a_dirigere_se_stessi.pdf",
        "portfolio_digitale.pdf"
      ],
      "confidence": "INFERRED",
      "relation": "conceptually_related_to",
      "why": "inferred connection - not explicitly stated in source; connects across different repos/directories; bridges separate communities"
    }
  ],
  "tokens": {
    "input": 84845,
    "output": 27222
  }
}